<?xml version="1.0" encoding="UTF-8" ?>
<DIDL-Lite xmlns="urn:schemas-upnp-org:metadata-1-0/DIDL-Lite" xmlns:dc="http://purl.org/dc/elements/1.1/" xmlns:upnp="urn:schemas-upnp-org:metadata-1-0/upnp">
<item>
  <upnp:class>object.item.audioItem.audioBroadcast</upnp:class>
  <dc:creator>Unknown</dc:creator>
  <dc:title>Rock Radio 101</dc:title>
  <upnp:genre>Rock</upnp:genre>
  <dc:description>Russian Rock Station - Album-Oriented</dc:description>
  <upnp:region>Russia - Moscow</upnp:region>
  <dc:language>Russian</dc:language>
  <dc:relation>http://www.101.ru</dc:relation>
  <upnp:radioCallSign></upnp:radioCallSign>
  <upnp:radioStationID></upnp:radioStationID>
  <upnp:radioBand>Internet</upnp:radioBand>
  <res protocolInfo="http-get:*:audio/mpegurl:*" bitrate="8192">http://www.101.ru/rockradio64.m3u</res>
  <res protocolInfo="http-get:*:audio/mpegurl:*" bitrate="3072">http://www.101.ru/rockradio24.m3u</res>
</item>
</DIDL-Lite>
